<?xml version="1.0" encoding="UTF-8"?>
<UIStates>
    <Binder Show="Yes">
        <ShowCollections>No</ShowCollections>
        <SelectedCollection>0</SelectedCollection>
        <SubdocumentCounts>No</SubdocumentCounts>
        <ExpandedItems>
            <ItemID>7A583553-3A84-40D6-B9B9-0430B8CD3E39</ItemID>
            <ItemID>E93166CF-D418-46C0-9E00-9B0F52CBE589</ItemID>
            <ItemID>A990D340-8B32-4517-8774-146C3611D206</ItemID>
            <ItemID>B4C4E0EA-BC3B-4ED7-80C4-D0764EA7D217</ItemID>
            <ItemID>F794FDA5-501F-4AFC-A17E-2110FD85D0A0</ItemID>
            <ItemID>8B95DA32-19DE-465E-A4C1-1E9BBF9077CF</ItemID>
            <ItemID>E2086D42-F859-4801-B737-5CF4398D6437</ItemID>
            <ItemID>2D059D8F-494A-45E6-9954-9E531EF07B6F</ItemID>
        </ExpandedItems>
        <Selection>
            <ItemID>E2086D42-F859-4801-B737-5CF4398D6437</ItemID>
        </Selection>
        <SearchResultsSort Titles="Ascending" Dates="Ascending">None</SearchResultsSort>
    </Binder>
    <Inspector Show="Yes" View="MetaData">
        <ShowProjectBookmarks>No</ShowProjectBookmarks>
        <ShowSimilarTexts>No</ShowSimilarTexts>
        <FootnoteNumbers Prompt="No">No</FootnoteNumbers>
    </Inspector>
    <Split>None</Split>
    <BinderAffects>Current</BinderAffects>
    <Labels>
        <Binder FullWidth="No">No</Binder>
        <Icons>No</Icons>
        <IndexCards>No</IndexCards>
        <OutlinerRows>No</OutlinerRows>
        <ScriveningsTitles>No</ScriveningsTitles>
    </Labels>
    <Corkboards>
        <LabelIndicators>Yes</LabelIndicators>
        <Stamps>No</Stamps>
        <Keywords>No</Keywords>
        <Numbers Restart="No">No</Numbers>
        <SnapToGrid>No</SnapToGrid>
        <BlankCardsAsGhosts>No</BlankCardsAsGhosts>
    </Corkboards>
    <Text>
        <ShowFormatBar>Yes</ShowFormatBar>
        <UseVerticalLayout>No</UseVerticalLayout>
        <ShowScriveningsTitles>No</ShowScriveningsTitles>
        <ShowInvisibles>Yes</ShowInvisibles>
        <RevisionMode>0</RevisionMode>
        <TextChecking>
            <Spelling>Yes</Spelling>
            <Grammar>Yes</Grammar>
            <SmartQuotes>Yes</SmartQuotes>
            <SmartDashes>No</SmartDashes>
        </TextChecking>
    </Text>
    <FullScreen>
        <ShowRuler>No</ShowRuler>
        <PageLayout Facing="No">No</PageLayout>
        <TypewriterScrolling>Yes</TypewriterScrolling>
    </FullScreen>
    <Editors Primary="Editor1">
        <Editor1>
            <View>
                <ShowHeader>Yes</ShowHeader>
                <ShowFooter>Yes</ShowFooter>
                <GroupsViewMode>Scrivenings</GroupsViewMode>
                <CurrentViewMode>Scrivenings</CurrentViewMode>
                <SelectionAffects>None</SelectionAffects>
                <Content>
                    <ItemID>E2086D42-F859-4801-B737-5CF4398D6437</ItemID>
                </Content>
                <NavigationHistory CurrentIndex="99">
                    <HistoryItem Type="BinderItems" ViewMode="Scrivenings" ScriveningsSelection="0,0">7C295420-4A38-4A5B-A5FA-C59D3C931CF6</HistoryItem>
                    <HistoryItem Type="BinderItems" ViewMode="Scrivenings" ScriveningsSelection="0,0">448D5C1E-6082-4C3A-9D60-207901555C72</HistoryItem>
                    <HistoryItem Type="BinderItems" ViewMode="Scrivenings" ScriveningsSelection="0,0">0BC1D249-0FAD-4212-B5B6-5CFD76784516</HistoryItem>
                    <HistoryItem Type="BinderItems" ViewMode="Scrivenings" ScriveningsSelection="0,0">AE4231C2-EC93-4F31-9CE7-BEB2CFA566FE</HistoryItem>
                    <HistoryItem Type="BinderItems" ViewMode="Scrivenings" ScriveningsSelection="0,0">0BC1D249-0FAD-4212-B5B6-5CFD76784516</HistoryItem>
                    <HistoryItem Type="BinderItems" ViewMode="Scrivenings" ScriveningsSelection="0,0">AE4231C2-EC93-4F31-9CE7-BEB2CFA566FE</HistoryItem>
                    <HistoryItem Type="BinderItems" ViewMode="Scrivenings" ScriveningsSelection="0,0">B21048FC-320A-4D60-A581-12B93A53998E</HistoryItem>
                    <HistoryItem Type="BinderItems" ViewMode="Scrivenings" ScriveningsSelection="0,0">D93F8387-A861-46C6-84AB-8DEC1563F84A</HistoryItem>
                    <HistoryItem Type="BinderItems" ViewMode="Scrivenings" ScriveningsSelection="0,0">8D3ACAC0-D3C2-44E6-86D0-2026E120E330</HistoryItem>
                    <HistoryItem Type="BinderItems" ViewMode="Scrivenings" ScriveningsSelection="0,0">F5E2724E-1C74-47BC-8DBB-7CA3AD6064D9</HistoryItem>
                    <HistoryItem Type="BinderItems" ViewMode="Scrivenings" ScriveningsSelection="0,0">B21048FC-320A-4D60-A581-12B93A53998E</HistoryItem>
                    <HistoryItem Type="BinderItems" ViewMode="Scrivenings" ScriveningsSelection="0,0">F5E2724E-1C74-47BC-8DBB-7CA3AD6064D9</HistoryItem>
                    <HistoryItem Type="BinderItems" ViewMode="Scrivenings" ScriveningsSelection="0,0">B21048FC-320A-4D60-A581-12B93A53998E</HistoryItem>
                    <HistoryItem Type="BinderItems" ViewMode="Scrivenings" ScriveningsSelection="0,0">B21048FC-320A-4D60-A581-12B93A53998E,F5E2724E-1C74-47BC-8DBB-7CA3AD6064D9,E2086D42-F859-4801-B737-5CF4398D6437</HistoryItem>
                    <HistoryItem Type="BinderItems" ViewMode="Scrivenings" ScriveningsSelection="0,0">46446F36-4033-4154-ACE1-AAC013FB5240</HistoryItem>
                    <HistoryItem Type="BinderItems" ViewMode="Scrivenings" ScriveningsSelection="0,0">F5E2724E-1C74-47BC-8DBB-7CA3AD6064D9</HistoryItem>
                    <HistoryItem Type="BinderItems" ViewMode="Scrivenings" ScriveningsSelection="0,0">899D8A2F-68AF-4464-B922-D8DE01CB5700</HistoryItem>
                    <HistoryItem Type="BinderItems" ViewMode="Scrivenings" ScriveningsSelection="0,0">2D003243-E242-4F27-9AC9-B07357BE907D</HistoryItem>
                    <HistoryItem Type="BinderItems" ViewMode="Scrivenings" ScriveningsSelection="0,0">7C295420-4A38-4A5B-A5FA-C59D3C931CF6</HistoryItem>
                    <HistoryItem Type="BinderItems" ViewMode="Scrivenings" ScriveningsSelection="0,0">448D5C1E-6082-4C3A-9D60-207901555C72</HistoryItem>
                    <HistoryItem Type="BinderItems" ViewMode="Single">189C70F7-1867-4E4D-BA23-A397641593A5</HistoryItem>
                    <HistoryItem Type="BinderItems" ViewMode="Scrivenings" ScriveningsSelection="0,0">997A4ACA-FF05-46BC-B8C0-266CCA4D412C</HistoryItem>
                    <HistoryItem Type="BinderItems" ViewMode="Scrivenings" ScriveningsSelection="0,0">B558A8AC-E568-4EC0-8A2A-D1B1E3434154</HistoryItem>
                    <HistoryItem Type="BinderItems" ViewMode="Scrivenings" ScriveningsSelection="0,0">448D5C1E-6082-4C3A-9D60-207901555C72</HistoryItem>
                    <HistoryItem Type="BinderItems" ViewMode="Scrivenings" ScriveningsSelection="0,0">F794FDA5-501F-4AFC-A17E-2110FD85D0A0</HistoryItem>
                    <HistoryItem Type="BinderItems" ViewMode="Scrivenings" ScriveningsSelection="0,0">448D5C1E-6082-4C3A-9D60-207901555C72</HistoryItem>
                    <HistoryItem Type="BinderItems" ViewMode="Scrivenings" ScriveningsSelection="0,0">8B95DA32-19DE-465E-A4C1-1E9BBF9077CF</HistoryItem>
                    <HistoryItem Type="BinderItems" ViewMode="Scrivenings" ScriveningsSelection="0,0">448D5C1E-6082-4C3A-9D60-207901555C72</HistoryItem>
                    <HistoryItem Type="BinderItems" ViewMode="Single">4A2FCE01-CDB5-46AB-ACAA-4A72332E0B6F</HistoryItem>
                    <HistoryItem Type="BinderItems" ViewMode="Scrivenings" ScriveningsSelection="0,0">B8EB6175-E365-46BA-912F-D0D9C0BDFF3A</HistoryItem>
                    <HistoryItem Type="BinderItems" ViewMode="Scrivenings" ScriveningsSelection="0,0">B4C4E0EA-BC3B-4ED7-80C4-D0764EA7D217</HistoryItem>
                    <HistoryItem Type="BinderItems" ViewMode="Scrivenings" ScriveningsSelection="0,0">88E114D4-2808-4654-ABCF-B2E6073257A2</HistoryItem>
                    <HistoryItem Type="BinderItems" ViewMode="Scrivenings" ScriveningsSelection="0,0">899D8A2F-68AF-4464-B922-D8DE01CB5700</HistoryItem>
                    <HistoryItem Type="BinderItems" ViewMode="Scrivenings" ScriveningsSelection="0,0">2D003243-E242-4F27-9AC9-B07357BE907D</HistoryItem>
                    <HistoryItem Type="BinderItems" ViewMode="Scrivenings" ScriveningsSelection="0,0">7C295420-4A38-4A5B-A5FA-C59D3C931CF6</HistoryItem>
                    <HistoryItem Type="BinderItems" ViewMode="Scrivenings" ScriveningsSelection="0,0">448D5C1E-6082-4C3A-9D60-207901555C72</HistoryItem>
                    <HistoryItem Type="BinderItems" ViewMode="Scrivenings" ScriveningsSelection="0,0">261B3A94-BF5F-4195-88CA-546062E3949A</HistoryItem>
                    <HistoryItem Type="BinderItems" ViewMode="Scrivenings" ScriveningsSelection="0,0">13459284-A416-45AB-A308-F267C2C78B12</HistoryItem>
                    <HistoryItem Type="BinderItems" ViewMode="Scrivenings" ScriveningsSelection="0,0">7C295420-4A38-4A5B-A5FA-C59D3C931CF6</HistoryItem>
                    <HistoryItem Type="BinderItems" ViewMode="Scrivenings" ScriveningsSelection="0,0">448D5C1E-6082-4C3A-9D60-207901555C72</HistoryItem>
                    <HistoryItem Type="BinderItems" ViewMode="Scrivenings" ScriveningsSelection="0,0">261B3A94-BF5F-4195-88CA-546062E3949A</HistoryItem>
                    <HistoryItem Type="BinderItems" ViewMode="Scrivenings" ScriveningsSelection="0,0">B21048FC-320A-4D60-A581-12B93A53998E</HistoryItem>
                    <HistoryItem Type="BinderItems" ViewMode="Scrivenings" ScriveningsSelection="0,0">261B3A94-BF5F-4195-88CA-546062E3949A</HistoryItem>
                    <HistoryItem Type="BinderItems" ViewMode="Scrivenings" ScriveningsSelection="0,0">B21048FC-320A-4D60-A581-12B93A53998E</HistoryItem>
                    <HistoryItem Type="BinderItems" ViewMode="Scrivenings" ScriveningsSelection="0,0">F5E2724E-1C74-47BC-8DBB-7CA3AD6064D9</HistoryItem>
                    <HistoryItem Type="BinderItems" ViewMode="Scrivenings" ScriveningsSelection="0,0">B21048FC-320A-4D60-A581-12B93A53998E</HistoryItem>
                    <HistoryItem Type="BinderItems" ViewMode="Scrivenings" ScriveningsSelection="0,0">F5E2724E-1C74-47BC-8DBB-7CA3AD6064D9</HistoryItem>
                    <HistoryItem Type="BinderItems" ViewMode="Scrivenings" ScriveningsSelection="0,0">E2086D42-F859-4801-B737-5CF4398D6437</HistoryItem>
                    <HistoryItem Type="BinderItems" ViewMode="Scrivenings" ScriveningsSelection="0,0">F5E2724E-1C74-47BC-8DBB-7CA3AD6064D9</HistoryItem>
                    <HistoryItem Type="BinderItems" ViewMode="Scrivenings" ScriveningsSelection="0,0">997A4ACA-FF05-46BC-B8C0-266CCA4D412C</HistoryItem>
                    <HistoryItem Type="BinderItems" ViewMode="Scrivenings" ScriveningsSelection="0,0">B8EB6175-E365-46BA-912F-D0D9C0BDFF3A</HistoryItem>
                    <HistoryItem Type="BinderItems" ViewMode="Scrivenings" ScriveningsSelection="0,0">997A4ACA-FF05-46BC-B8C0-266CCA4D412C</HistoryItem>
                    <HistoryItem Type="BinderItems" ViewMode="Scrivenings" ScriveningsSelection="0,0">F5E2724E-1C74-47BC-8DBB-7CA3AD6064D9</HistoryItem>
                    <HistoryItem Type="BinderItems" ViewMode="Scrivenings" ScriveningsSelection="0,0">46446F36-4033-4154-ACE1-AAC013FB5240</HistoryItem>
                    <HistoryItem Type="BinderItems" ViewMode="Scrivenings" ScriveningsSelection="0,0">AE4231C2-EC93-4F31-9CE7-BEB2CFA566FE</HistoryItem>
                    <HistoryItem Type="BinderItems" ViewMode="Scrivenings" ScriveningsSelection="0,0">997A4ACA-FF05-46BC-B8C0-266CCA4D412C</HistoryItem>
                    <HistoryItem Type="BinderItems" ViewMode="Scrivenings" ScriveningsSelection="0,0">F794FDA5-501F-4AFC-A17E-2110FD85D0A0</HistoryItem>
                    <HistoryItem Type="BinderItems" ViewMode="Scrivenings" ScriveningsSelection="0,0">A990D340-8B32-4517-8774-146C3611D206</HistoryItem>
                    <HistoryItem Type="BinderItems" ViewMode="Scrivenings" ScriveningsSelection="0,0">AF841D75-092B-47D0-B576-25BF61C4385A</HistoryItem>
                    <HistoryItem Type="BinderItems" ViewMode="Scrivenings" ScriveningsSelection="0,0">B4C4E0EA-BC3B-4ED7-80C4-D0764EA7D217</HistoryItem>
                    <HistoryItem Type="BinderItems" ViewMode="Scrivenings" ScriveningsSelection="0,0">B8EB6175-E365-46BA-912F-D0D9C0BDFF3A</HistoryItem>
                    <HistoryItem Type="BinderItems" ViewMode="Scrivenings" ScriveningsSelection="0,0">B558A8AC-E568-4EC0-8A2A-D1B1E3434154</HistoryItem>
                    <HistoryItem Type="BinderItems" ViewMode="Scrivenings" ScriveningsSelection="0,0">43C25DE4-5C73-4137-BC8C-2843BE82AD7A</HistoryItem>
                    <HistoryItem Type="BinderItems" ViewMode="Scrivenings" ScriveningsSelection="0,0">A990D340-8B32-4517-8774-146C3611D206</HistoryItem>
                    <HistoryItem Type="BinderItems" ViewMode="Scrivenings" ScriveningsSelection="0,0">B4C4E0EA-BC3B-4ED7-80C4-D0764EA7D217</HistoryItem>
                    <HistoryItem Type="BinderItems" ViewMode="Single">12CC6420-441F-483D-B054-1E5824EB0DFB</HistoryItem>
                    <HistoryItem Type="BinderItems" ViewMode="Scrivenings" ScriveningsSelection="0,0">F794FDA5-501F-4AFC-A17E-2110FD85D0A0</HistoryItem>
                    <HistoryItem Type="BinderItems" ViewMode="Scrivenings" ScriveningsSelection="0,0">B4C4E0EA-BC3B-4ED7-80C4-D0764EA7D217</HistoryItem>
                    <HistoryItem Type="BinderItems" ViewMode="Single">834D3E25-7549-496D-B6FC-B6850D8B8841</HistoryItem>
                    <HistoryItem Type="BinderItems" ViewMode="Scrivenings" ScriveningsSelection="0,0">F794FDA5-501F-4AFC-A17E-2110FD85D0A0</HistoryItem>
                    <HistoryItem Type="BinderItems" ViewMode="Scrivenings" ScriveningsSelection="0,0">B4C4E0EA-BC3B-4ED7-80C4-D0764EA7D217</HistoryItem>
                    <HistoryItem Type="BinderItems" ViewMode="Scrivenings" ScriveningsSelection="0,0">AF841D75-092B-47D0-B576-25BF61C4385A</HistoryItem>
                    <HistoryItem Type="BinderItems" ViewMode="Scrivenings" ScriveningsSelection="0,0">B4C4E0EA-BC3B-4ED7-80C4-D0764EA7D217</HistoryItem>
                    <HistoryItem Type="BinderItems" ViewMode="Scrivenings" ScriveningsSelection="0,0">F794FDA5-501F-4AFC-A17E-2110FD85D0A0</HistoryItem>
                    <HistoryItem Type="BinderItems" ViewMode="Scrivenings" ScriveningsSelection="0,0">997A4ACA-FF05-46BC-B8C0-266CCA4D412C</HistoryItem>
                    <HistoryItem Type="BinderItems" ViewMode="Scrivenings" ScriveningsSelection="0,0">F794FDA5-501F-4AFC-A17E-2110FD85D0A0</HistoryItem>
                    <HistoryItem Type="BinderItems" ViewMode="Scrivenings" ScriveningsSelection="0,0">43C25DE4-5C73-4137-BC8C-2843BE82AD7A</HistoryItem>
                    <HistoryItem Type="BinderItems" ViewMode="Scrivenings" ScriveningsSelection="0,0">F794FDA5-501F-4AFC-A17E-2110FD85D0A0</HistoryItem>
                    <HistoryItem Type="BinderItems" ViewMode="Scrivenings" ScriveningsSelection="0,0">997A4ACA-FF05-46BC-B8C0-266CCA4D412C</HistoryItem>
                    <HistoryItem Type="BinderItems" ViewMode="Scrivenings" ScriveningsSelection="0,0">F794FDA5-501F-4AFC-A17E-2110FD85D0A0</HistoryItem>
                    <HistoryItem Type="BinderItems" ViewMode="Scrivenings" ScriveningsSelection="0,0">B558A8AC-E568-4EC0-8A2A-D1B1E3434154</HistoryItem>
                    <HistoryItem Type="BinderItems" ViewMode="Scrivenings" ScriveningsSelection="0,0">43C25DE4-5C73-4137-BC8C-2843BE82AD7A</HistoryItem>
                    <HistoryItem Type="BinderItems" ViewMode="Scrivenings" ScriveningsSelection="0,0">8B95DA32-19DE-465E-A4C1-1E9BBF9077CF</HistoryItem>
                    <HistoryItem Type="BinderItems" ViewMode="Scrivenings" ScriveningsSelection="0,0">88E114D4-2808-4654-ABCF-B2E6073257A2</HistoryItem>
                    <HistoryItem Type="BinderItems" ViewMode="Scrivenings" ScriveningsSelection="0,0">899D8A2F-68AF-4464-B922-D8DE01CB5700</HistoryItem>
                    <HistoryItem Type="BinderItems" ViewMode="Scrivenings" ScriveningsSelection="0,0">46446F36-4033-4154-ACE1-AAC013FB5240</HistoryItem>
                    <HistoryItem Type="BinderItems" ViewMode="Scrivenings" ScriveningsSelection="0,0">13459284-A416-45AB-A308-F267C2C78B12</HistoryItem>
                    <HistoryItem Type="BinderItems" ViewMode="Scrivenings" ScriveningsSelection="0,0">E2086D42-F859-4801-B737-5CF4398D6437</HistoryItem>
                    <HistoryItem Type="BinderItems" ViewMode="Scrivenings" ScriveningsSelection="0,0">13459284-A416-45AB-A308-F267C2C78B12</HistoryItem>
                    <HistoryItem Type="BinderItems" ViewMode="Scrivenings" ScriveningsSelection="0,0">46446F36-4033-4154-ACE1-AAC013FB5240</HistoryItem>
                    <HistoryItem Type="BinderItems" ViewMode="Scrivenings" ScriveningsSelection="0,0">E2086D42-F859-4801-B737-5CF4398D6437</HistoryItem>
                    <HistoryItem Type="BinderItems" ViewMode="Scrivenings" ScriveningsSelection="0,0">D507EA60-FEC9-4A37-A632-DC18C72DC7E1</HistoryItem>
                    <HistoryItem Type="BinderItems" ViewMode="Scrivenings" ScriveningsSelection="0,0">98E68C2A-F4D3-4A48-A8A5-FE7E1A55CD83</HistoryItem>
                    <HistoryItem Type="BinderItems" ViewMode="Scrivenings" ScriveningsSelection="0,0">D507EA60-FEC9-4A37-A632-DC18C72DC7E1</HistoryItem>
                    <HistoryItem Type="BinderItems" ViewMode="Scrivenings" ScriveningsSelection="0,0">D507EA60-FEC9-4A37-A632-DC18C72DC7E1,98E68C2A-F4D3-4A48-A8A5-FE7E1A55CD83,9D5FBD2F-F4F0-4943-8D3C-67C7A2188BCF</HistoryItem>
                    <HistoryItem Type="BinderItems" ViewMode="Scrivenings" ScriveningsSelection="0,0">E2086D42-F859-4801-B737-5CF4398D6437</HistoryItem>
                    <HistoryItem Type="BinderItems" ViewMode="Single">98E68C2A-F4D3-4A48-A8A5-FE7E1A55CD83</HistoryItem>
                    <HistoryItem Type="BinderItems" ViewMode="Single">9D5FBD2F-F4F0-4943-8D3C-67C7A2188BCF</HistoryItem>
                    <HistoryItem Type="BinderItems" ViewMode="Single">D507EA60-FEC9-4A37-A632-DC18C72DC7E1</HistoryItem>
                    <HistoryItem Type="BinderItems" ViewMode="Scrivenings">E2086D42-F859-4801-B737-5CF4398D6437</HistoryItem>
                </NavigationHistory>
            </View>
            <Text>
                <ShowRuler>Yes</ShowRuler>
                <PageLayout Facing="No">No</PageLayout>
                <TypewriterScrolling>No</TypewriterScrolling>
                <LineNumbers Interval="1">No</LineNumbers>
                <Selection>294,0</Selection>
            </Text>
            <Outliner>
                <Columns>
                    <ColID>title</ColID>
                    <ColID>label</ColID>
                    <ColID>status</ColID>
                    <ColID>sectionType</ColID>
                    <ColID>totalTargetCount</ColID>
                    <ColID>totalProgress</ColID>
                </Columns>
                <ExpandedItems>
                    <ItemID>1114FD12-E46B-4C2E-BB5F-177EFC827EB6</ItemID>
                    <ItemID>A8956FA7-6C37-4DE2-B2B7-08F7248C1E94</ItemID>
                    <ItemID>6C3BDCCC-F6C3-4AF9-B7CD-475616712EAE</ItemID>
                </ExpandedItems>
                <TitlesOnly>No</TitlesOnly>
                <HideIcons>No</HideIcons>
                <ShowNumbers>No</ShowNumbers>
                <KeywordsAsChips>Yes</KeywordsAsChips>
                <FixedRowHeights>No</FixedRowHeights>
            </Outliner>
            <Corkboard>
                <CardsAcross>-1</CardsAcross>
                <KeywordChips>5</KeywordChips>
                <SizeCardsToFit>Yes</SizeCardsToFit>
                <CardHeightRatio>0.6666</CardHeightRatio>
                <SectionsArrangement>Wrap</SectionsArrangement>
                <LabelThreadsUseColumns>No</LabelThreadsUseColumns>
            </Corkboard>
            <Copyholder PreferredOrientation="Vertical" VerticalPos="Right" HorizontalPos="Bottom">
                <Text>
                    <ShowRuler>No</ShowRuler>
                    <PageLayout Facing="No">No</PageLayout>
                    <TypewriterScrolling>No</TypewriterScrolling>
                    <LineNumbers Interval="1">No</LineNumbers>
                </Text>
            </Copyholder>
        </Editor1>
        <Editor2>
            <View>
                <ShowHeader>Yes</ShowHeader>
                <ShowFooter>Yes</ShowFooter>
                <GroupsViewMode>Scrivenings</GroupsViewMode>
                <CurrentViewMode>Single</CurrentViewMode>
                <SelectionAffects>None</SelectionAffects>
                <NavigationHistory CurrentIndex="0"/>
            </View>
            <Text>
                <ShowRuler>Yes</ShowRuler>
                <PageLayout Facing="No">No</PageLayout>
                <TypewriterScrolling>No</TypewriterScrolling>
                <LineNumbers Interval="1">No</LineNumbers>
                <Selection>0,0</Selection>
            </Text>
            <Outliner>
                <Columns>
                    <ColID>title</ColID>
                    <ColID>label</ColID>
                    <ColID>status</ColID>
                    <ColID>sectionType</ColID>
                    <ColID>totalTargetCount</ColID>
                    <ColID>totalProgress</ColID>
                </Columns>
                <TitlesOnly>No</TitlesOnly>
                <HideIcons>No</HideIcons>
                <ShowNumbers>No</ShowNumbers>
                <KeywordsAsChips>Yes</KeywordsAsChips>
                <FixedRowHeights>No</FixedRowHeights>
            </Outliner>
            <Corkboard>
                <CardsAcross>-1</CardsAcross>
                <KeywordChips>5</KeywordChips>
                <SizeCardsToFit>Yes</SizeCardsToFit>
                <CardHeightRatio>0.6666</CardHeightRatio>
                <SectionsArrangement>Wrap</SectionsArrangement>
                <LabelThreadsUseColumns>No</LabelThreadsUseColumns>
            </Corkboard>
            <Copyholder PreferredOrientation="Vertical" VerticalPos="Right" HorizontalPos="Bottom">
                <Text>
                    <ShowRuler>No</ShowRuler>
                    <PageLayout Facing="No">No</PageLayout>
                    <TypewriterScrolling>No</TypewriterScrolling>
                    <LineNumbers Interval="1">No</LineNumbers>
                </Text>
            </Copyholder>
        </Editor2>
    </Editors>
</UIStates>