<?xml version="1.0" encoding="UTF-8"?>
<UIStates>
    <Binder Show="Yes">
        <ShowCollections>No</ShowCollections>
        <SelectedCollection>0</SelectedCollection>
        <SubdocumentCounts>No</SubdocumentCounts>
        <ExpandedItems>
            <ItemID>7A583553-3A84-40D6-B9B9-0430B8CD3E39</ItemID>
            <ItemID>AC51926B-976D-4AA1-A002-712B28714F4C</ItemID>
            <ItemID>F2B2723C-CDC8-4C35-90B7-BCD557B66E9A</ItemID>
            <ItemID>1965642B-B063-4E9C-905A-C99F4C87FBEA</ItemID>
            <ItemID>7E7A14F1-560C-4645-B414-66E789EF99E9</ItemID>
            <ItemID>86E448C7-AB0D-4824-9745-BF3635EA332E</ItemID>
            <ItemID>8EAD4254-A3DA-4CCA-A68C-C56E225294CF</ItemID>
            <ItemID>E93166CF-D418-46C0-9E00-9B0F52CBE589</ItemID>
            <ItemID>37EDAD9A-63E9-4F5E-A436-DE4520E3B622</ItemID>
            <ItemID>5823802B-C704-42B3-AD53-70CB7283790B</ItemID>
            <ItemID>F32091D5-63D9-4B78-B9A0-4F966A7F8004</ItemID>
            <ItemID>98AB2B8D-DCDB-44ED-B650-63C8F1B6E92E</ItemID>
            <ItemID>463FDA98-8F2C-4E81-AB33-81ABE1636216</ItemID>
            <ItemID>128B4AC0-E0F0-496B-85AB-1F613FBBFEF2</ItemID>
            <ItemID>3A093557-4510-4BCC-A09E-66665616270F</ItemID>
            <ItemID>8D3ACAC0-D3C2-44E6-86D0-2026E120E330</ItemID>
            <ItemID>08A84778-8F8D-4216-987B-4F3335C94084</ItemID>
            <ItemID>93FFE8C7-2CC7-4A13-AA36-AF03BB078BE0</ItemID>
            <ItemID>2396AEC7-B4DC-4946-BA72-5A07420AA072</ItemID>
            <ItemID>43F1E991-B19E-4467-80F8-D856BE9C6D09</ItemID>
            <ItemID>A41BA2A1-C599-43C2-99CC-8C1A7FFC2C24</ItemID>
            <ItemID>0348DE80-DE65-4463-84A0-8E513365C8ED</ItemID>
            <ItemID>A7B290B8-7785-4EC8-A2A1-291CC6ED8CA6</ItemID>
        </ExpandedItems>
        <Selection>
            <ItemID>3CAFE294-7794-4E86-A7F5-D32E73C1EAFE</ItemID>
        </Selection>
        <SearchResultsSort Titles="Ascending" Dates="Ascending">None</SearchResultsSort>
    </Binder>
    <Inspector Show="Yes" View="MetaData">
        <ShowProjectBookmarks>No</ShowProjectBookmarks>
        <ShowSimilarTexts>No</ShowSimilarTexts>
        <Collapse>Keywords</Collapse>
        <FootnoteNumbers Prompt="No">No</FootnoteNumbers>
    </Inspector>
    <Split>None</Split>
    <BinderAffects>Current</BinderAffects>
    <Labels>
        <Binder FullWidth="No">No</Binder>
        <Icons>No</Icons>
        <IndexCards>No</IndexCards>
        <OutlinerRows>No</OutlinerRows>
        <ScriveningsTitles>No</ScriveningsTitles>
    </Labels>
    <Corkboards>
        <LabelIndicators>Yes</LabelIndicators>
        <Stamps>No</Stamps>
        <Keywords>No</Keywords>
        <Numbers Restart="No">No</Numbers>
        <SnapToGrid>No</SnapToGrid>
        <BlankCardsAsGhosts>No</BlankCardsAsGhosts>
    </Corkboards>
    <Text>
        <ShowFormatBar>Yes</ShowFormatBar>
        <UseVerticalLayout>No</UseVerticalLayout>
        <ShowScriveningsTitles>No</ShowScriveningsTitles>
        <ShowInvisibles>Yes</ShowInvisibles>
        <RevisionMode>0</RevisionMode>
        <TextChecking>
            <Spelling>Yes</Spelling>
            <Grammar>Yes</Grammar>
            <SmartQuotes>No</SmartQuotes>
            <SmartDashes>No</SmartDashes>
        </TextChecking>
    </Text>
    <FullScreen>
        <ShowRuler>No</ShowRuler>
        <PageLayout Facing="No">No</PageLayout>
        <TypewriterScrolling>Yes</TypewriterScrolling>
    </FullScreen>
    <Editors Primary="Editor2">
        <Editor1>
            <View>
                <ShowHeader>Yes</ShowHeader>
                <ShowFooter>Yes</ShowFooter>
                <GroupsViewMode>Single</GroupsViewMode>
                <CurrentViewMode>Single</CurrentViewMode>
                <SelectionAffects>None</SelectionAffects>
                <NavigationHistory CurrentIndex="0"/>
            </View>
            <Text>
                <ShowRuler>Yes</ShowRuler>
                <PageLayout Facing="No">No</PageLayout>
                <TypewriterScrolling>No</TypewriterScrolling>
                <LineNumbers Interval="1">No</LineNumbers>
                <Selection>0,0</Selection>
            </Text>
            <Outliner>
                <Columns>
                    <ColID>title</ColID>
                    <ColID>label</ColID>
                    <ColID>status</ColID>
                    <ColID>sectionType</ColID>
                    <ColID>totalTargetCount</ColID>
                    <ColID>totalProgress</ColID>
                </Columns>
                <ExpandedItems>
                    <ItemID>1114FD12-E46B-4C2E-BB5F-177EFC827EB6</ItemID>
                    <ItemID>A8956FA7-6C37-4DE2-B2B7-08F7248C1E94</ItemID>
                    <ItemID>6C3BDCCC-F6C3-4AF9-B7CD-475616712EAE</ItemID>
                </ExpandedItems>
                <TitlesOnly>No</TitlesOnly>
                <HideIcons>No</HideIcons>
                <ShowNumbers>No</ShowNumbers>
                <KeywordsAsChips>Yes</KeywordsAsChips>
                <FixedRowHeights>No</FixedRowHeights>
            </Outliner>
            <Corkboard>
                <CardsAcross>-1</CardsAcross>
                <KeywordChips>5</KeywordChips>
                <SizeCardsToFit>Yes</SizeCardsToFit>
                <CardHeightRatio>0.6666</CardHeightRatio>
                <SectionsArrangement>Wrap</SectionsArrangement>
                <LabelThreadsUseColumns>No</LabelThreadsUseColumns>
            </Corkboard>
            <Copyholder PreferredOrientation="Vertical" VerticalPos="Right" HorizontalPos="Bottom">
                <Text>
                    <ShowRuler>No</ShowRuler>
                    <PageLayout Facing="No">No</PageLayout>
                    <TypewriterScrolling>No</TypewriterScrolling>
                    <LineNumbers Interval="1">No</LineNumbers>
                </Text>
            </Copyholder>
        </Editor1>
        <Editor2>
            <View>
                <ShowHeader>Yes</ShowHeader>
                <ShowFooter>Yes</ShowFooter>
                <GroupsViewMode>Single</GroupsViewMode>
                <CurrentViewMode>Single</CurrentViewMode>
                <SelectionAffects>None</SelectionAffects>
                <Content>
                    <ItemID>3CAFE294-7794-4E86-A7F5-D32E73C1EAFE</ItemID>
                </Content>
                <NavigationHistory CurrentIndex="99">
                    <HistoryItem Type="BinderItems" ViewMode="Single">C047CE17-DFB6-41DA-8A95-8964F9586DD1</HistoryItem>
                    <HistoryItem Type="BinderItems" ViewMode="Single">35A16A69-096B-4A89-B902-C82923F7FE82</HistoryItem>
                    <HistoryItem Type="BinderItems" ViewMode="Single">BCDCD87A-A0E8-4BF7-AB2A-5B9775FA4994</HistoryItem>
                    <HistoryItem Type="BinderItems" ViewMode="Single">ECDAF518-158C-4E99-B20C-A76DD4831DE8</HistoryItem>
                    <HistoryItem Type="BinderItems" ViewMode="Single">4144534E-1E4E-4BB3-87BE-BCCA637FA3CB</HistoryItem>
                    <HistoryItem Type="BinderItems" ViewMode="Single">32378D4E-2BA7-4BAC-8DA4-9F124FBD7E9E</HistoryItem>
                    <HistoryItem Type="BinderItems" ViewMode="Single">52446522-320C-457E-908C-6D2B6723A890</HistoryItem>
                    <HistoryItem Type="BinderItems" ViewMode="Single">35A16A69-096B-4A89-B902-C82923F7FE82</HistoryItem>
                    <HistoryItem Type="BinderItems" ViewMode="Scrivenings" ScriveningsSelection="0,0">AC51926B-976D-4AA1-A002-712B28714F4C</HistoryItem>
                    <HistoryItem Type="BinderItems" ViewMode="Scrivenings" ScriveningsSelection="0,0">7A583553-3A84-40D6-B9B9-0430B8CD3E39</HistoryItem>
                    <HistoryItem Type="BinderItems" ViewMode="Scrivenings" ScriveningsSelection="0,0">2396AEC7-B4DC-4946-BA72-5A07420AA072</HistoryItem>
                    <HistoryItem Type="BinderItems" ViewMode="Scrivenings" ScriveningsSelection="0,0">7E7A14F1-560C-4645-B414-66E789EF99E9</HistoryItem>
                    <HistoryItem Type="BinderItems" ViewMode="Scrivenings" ScriveningsSelection="0,0">E93166CF-D418-46C0-9E00-9B0F52CBE589</HistoryItem>
                    <HistoryItem Type="BinderItems" ViewMode="Scrivenings" ScriveningsSelection="0,0">9D380E83-3DCE-4B36-8F98-19DDADFDA2AB</HistoryItem>
                    <HistoryItem Type="BinderItems" ViewMode="Scrivenings" ScriveningsSelection="0,0">A990D340-8B32-4517-8774-146C3611D206</HistoryItem>
                    <HistoryItem Type="BinderItems" ViewMode="Scrivenings" ScriveningsSelection="0,0">7E7A14F1-560C-4645-B414-66E789EF99E9</HistoryItem>
                    <HistoryItem Type="BinderItems" ViewMode="Single">1AEEE489-8CF6-4E71-800D-20BF63D326A1</HistoryItem>
                    <HistoryItem Type="BinderItems" ViewMode="Scrivenings" ScriveningsSelection="0,0">1DA94CAA-3CCA-4990-9976-D222EFD92211</HistoryItem>
                    <HistoryItem Type="BinderItems" ViewMode="Scrivenings" ScriveningsSelection="0,0">7E7A14F1-560C-4645-B414-66E789EF99E9</HistoryItem>
                    <HistoryItem Type="BinderItems" ViewMode="Single">7121E58E-FDA4-4C8B-84A5-2CEC815A3195</HistoryItem>
                    <HistoryItem Type="BinderItems" ViewMode="Single">246BEBE5-0EA8-4CA8-B7FB-0E8BC84B9AA3</HistoryItem>
                    <HistoryItem Type="BinderItems" ViewMode="Single">1DA94CAA-3CCA-4990-9976-D222EFD92211</HistoryItem>
                    <HistoryItem Type="BinderItems" ViewMode="Single">A8B51DFA-405E-454A-974A-D24304CE631E</HistoryItem>
                    <HistoryItem Type="BinderItems" ViewMode="Scrivenings" ScriveningsSelection="0,0">7E7A14F1-560C-4645-B414-66E789EF99E9</HistoryItem>
                    <HistoryItem Type="BinderItems" ViewMode="Single">E0298280-6622-480B-905A-86466E8A2B6C</HistoryItem>
                    <HistoryItem Type="BinderItems" ViewMode="Single">B582CD91-57BE-475D-A81C-445260D02583</HistoryItem>
                    <HistoryItem Type="BinderItems" ViewMode="Single">6CEB1B86-3279-4C57-8136-6BB55BC4744A</HistoryItem>
                    <HistoryItem Type="BinderItems" ViewMode="Single">448D5C1E-6082-4C3A-9D60-207901555C72</HistoryItem>
                    <HistoryItem Type="BinderItems" ViewMode="Single">1E837A1F-E3FD-4130-A549-69070D241E53</HistoryItem>
                    <HistoryItem Type="BinderItems" ViewMode="Single">E04C59FA-A8ED-4221-8F69-07D8D84B46BC</HistoryItem>
                    <HistoryItem Type="BinderItems" ViewMode="Single">6D1AC369-5549-4029-B3A9-C6D9E02DDB2C</HistoryItem>
                    <HistoryItem Type="BinderItems" ViewMode="Single">B9644328-2F49-4027-AD6A-19B3CE9A849F</HistoryItem>
                    <HistoryItem Type="BinderItems" ViewMode="Single">56322086-ED9F-4FBE-A527-626C36C3BBA9</HistoryItem>
                    <HistoryItem Type="BinderItems" ViewMode="Single">15B6D460-608A-48C9-94B3-88A197779B22</HistoryItem>
                    <HistoryItem Type="BinderItems" ViewMode="Single">61305976-CB9F-43DE-857B-12C465851690</HistoryItem>
                    <HistoryItem Type="BinderItems" ViewMode="Single">6D1AC369-5549-4029-B3A9-C6D9E02DDB2C</HistoryItem>
                    <HistoryItem Type="BinderItems" ViewMode="Scrivenings" ScriveningsSelection="0,0">E0298280-6622-480B-905A-86466E8A2B6C</HistoryItem>
                    <HistoryItem Type="BinderItems" ViewMode="Scrivenings" ScriveningsSelection="0,0">7E7A14F1-560C-4645-B414-66E789EF99E9</HistoryItem>
                    <HistoryItem Type="BinderItems" ViewMode="Scrivenings" ScriveningsSelection="0,0">463FDA98-8F2C-4E81-AB33-81ABE1636216</HistoryItem>
                    <HistoryItem Type="BinderItems" ViewMode="Scrivenings" ScriveningsSelection="0,0">E97A970B-9077-4312-8B1E-07382D27A538</HistoryItem>
                    <HistoryItem Type="BinderItems" ViewMode="Single">9FFD125C-CA24-4A09-BB11-8792552B8462</HistoryItem>
                    <HistoryItem Type="BinderItems" ViewMode="Single">747F9F65-CCED-4A33-8221-619BB5DFFC8D</HistoryItem>
                    <HistoryItem Type="BinderItems" ViewMode="Single">CBA833CF-D873-4D52-B532-468FA0293852</HistoryItem>
                    <HistoryItem Type="BinderItems" ViewMode="Single">07437C0F-71BB-4A2F-A561-C62D73019135</HistoryItem>
                    <HistoryItem Type="BinderItems" ViewMode="Single">0D56D71F-069F-44BE-AC2F-6D6694D4BAA8</HistoryItem>
                    <HistoryItem Type="BinderItems" ViewMode="Single">9FFD125C-CA24-4A09-BB11-8792552B8462</HistoryItem>
                    <HistoryItem Type="BinderItems" ViewMode="Scrivenings" ScriveningsSelection="0,0">E223717E-D70B-449C-B2F9-BD8A841D3D3B</HistoryItem>
                    <HistoryItem Type="BinderItems" ViewMode="Single">747F9F65-CCED-4A33-8221-619BB5DFFC8D</HistoryItem>
                    <HistoryItem Type="BinderItems" ViewMode="Single">CBA833CF-D873-4D52-B532-468FA0293852</HistoryItem>
                    <HistoryItem Type="BinderItems" ViewMode="Single">0D56D71F-069F-44BE-AC2F-6D6694D4BAA8</HistoryItem>
                    <HistoryItem Type="BinderItems" ViewMode="Scrivenings" ScriveningsSelection="0,0">E223717E-D70B-449C-B2F9-BD8A841D3D3B</HistoryItem>
                    <HistoryItem Type="BinderItems" ViewMode="Scrivenings" ScriveningsSelection="0,0">86E29C7F-7E10-4BFF-882B-18AB34ABF54B</HistoryItem>
                    <HistoryItem Type="BinderItems" ViewMode="Scrivenings" ScriveningsSelection="0,0">E223717E-D70B-449C-B2F9-BD8A841D3D3B</HistoryItem>
                    <HistoryItem Type="BinderItems" ViewMode="Scrivenings" ScriveningsSelection="0,0">CD69884B-2EC7-4C32-AF6F-AA9DADC525FA</HistoryItem>
                    <HistoryItem Type="BinderItems" ViewMode="Scrivenings" ScriveningsSelection="0,0">986896F8-B69C-4D69-A19E-98F2B9E7DB97</HistoryItem>
                    <HistoryItem Type="BinderItems" ViewMode="Scrivenings" ScriveningsSelection="0,0">1BF4AF98-1670-4490-A9AA-5570DE96FA8E</HistoryItem>
                    <HistoryItem Type="BinderItems" ViewMode="Scrivenings" ScriveningsSelection="0,0">E223717E-D70B-449C-B2F9-BD8A841D3D3B</HistoryItem>
                    <HistoryItem Type="BinderItems" ViewMode="Scrivenings" ScriveningsSelection="0,0">86E29C7F-7E10-4BFF-882B-18AB34ABF54B</HistoryItem>
                    <HistoryItem Type="BinderItems" ViewMode="Scrivenings" ScriveningsSelection="0,0">986896F8-B69C-4D69-A19E-98F2B9E7DB97</HistoryItem>
                    <HistoryItem Type="BinderItems" ViewMode="Scrivenings" ScriveningsSelection="0,0">CD69884B-2EC7-4C32-AF6F-AA9DADC525FA</HistoryItem>
                    <HistoryItem Type="BinderItems" ViewMode="Scrivenings" ScriveningsSelection="0,0">986896F8-B69C-4D69-A19E-98F2B9E7DB97</HistoryItem>
                    <HistoryItem Type="BinderItems" ViewMode="Scrivenings" ScriveningsSelection="0,0">CD69884B-2EC7-4C32-AF6F-AA9DADC525FA</HistoryItem>
                    <HistoryItem Type="BinderItems" ViewMode="Scrivenings" ScriveningsSelection="0,0">E0164142-9BA4-4423-A825-725BC64D7745</HistoryItem>
                    <HistoryItem Type="BinderItems" ViewMode="Single">6D1AC369-5549-4029-B3A9-C6D9E02DDB2C</HistoryItem>
                    <HistoryItem Type="BinderItems" ViewMode="Scrivenings" ScriveningsSelection="0,0">7CED0421-D524-49E7-B90A-0CBF08FB141C</HistoryItem>
                    <HistoryItem Type="BinderItems" ViewMode="Scrivenings" ScriveningsSelection="0,0">E0298280-6622-480B-905A-86466E8A2B6C</HistoryItem>
                    <HistoryItem Type="BinderItems" ViewMode="Scrivenings" ScriveningsSelection="0,0">463FDA98-8F2C-4E81-AB33-81ABE1636216</HistoryItem>
                    <HistoryItem Type="BinderItems" ViewMode="Scrivenings" ScriveningsSelection="0,0">8EAD4254-A3DA-4CCA-A68C-C56E225294CF</HistoryItem>
                    <HistoryItem Type="BinderItems" ViewMode="Single">B9644328-2F49-4027-AD6A-19B3CE9A849F</HistoryItem>
                    <HistoryItem Type="BinderItems" ViewMode="Single">6D1AC369-5549-4029-B3A9-C6D9E02DDB2C</HistoryItem>
                    <HistoryItem Type="BinderItems" ViewMode="Scrivenings" ScriveningsSelection="0,0">7CED0421-D524-49E7-B90A-0CBF08FB141C</HistoryItem>
                    <HistoryItem Type="BinderItems" ViewMode="Scrivenings" ScriveningsSelection="0,0">E0298280-6622-480B-905A-86466E8A2B6C</HistoryItem>
                    <HistoryItem Type="BinderItems" ViewMode="Single">15B6D460-608A-48C9-94B3-88A197779B22</HistoryItem>
                    <HistoryItem Type="BinderItems" ViewMode="Single">3F8731E5-6263-4834-BE85-B1E44A37C0E4</HistoryItem>
                    <HistoryItem Type="BinderItems" ViewMode="Scrivenings" ScriveningsSelection="0,0">98AB2B8D-DCDB-44ED-B650-63C8F1B6E92E</HistoryItem>
                    <HistoryItem Type="BinderItems" ViewMode="Single">86E29C7F-7E10-4BFF-882B-18AB34ABF54B</HistoryItem>
                    <HistoryItem Type="BinderItems" ViewMode="Single">E0164142-9BA4-4423-A825-725BC64D7745</HistoryItem>
                    <HistoryItem Type="BinderItems" ViewMode="Single">A1BEAE42-5915-4E38-8710-DF56B949AFE0</HistoryItem>
                    <HistoryItem Type="BinderItems" ViewMode="Single">CD69884B-2EC7-4C32-AF6F-AA9DADC525FA</HistoryItem>
                    <HistoryItem Type="BinderItems" ViewMode="Scrivenings" ScriveningsSelection="0,0">E0164142-9BA4-4423-A825-725BC64D7745</HistoryItem>
                    <HistoryItem Type="BinderItems" ViewMode="Scrivenings" ScriveningsSelection="0,0">A1BEAE42-5915-4E38-8710-DF56B949AFE0</HistoryItem>
                    <HistoryItem Type="BinderItems" ViewMode="Scrivenings" ScriveningsSelection="0,0">CD69884B-2EC7-4C32-AF6F-AA9DADC525FA</HistoryItem>
                    <HistoryItem Type="BinderItems" ViewMode="Scrivenings" ScriveningsSelection="0,0">986896F8-B69C-4D69-A19E-98F2B9E7DB97</HistoryItem>
                    <HistoryItem Type="BinderItems" ViewMode="Scrivenings" ScriveningsSelection="0,0">CD69884B-2EC7-4C32-AF6F-AA9DADC525FA</HistoryItem>
                    <HistoryItem Type="BinderItems" ViewMode="Single">747F9F65-CCED-4A33-8221-619BB5DFFC8D</HistoryItem>
                    <HistoryItem Type="BinderItems" ViewMode="Single">CBA833CF-D873-4D52-B532-468FA0293852</HistoryItem>
                    <HistoryItem Type="BinderItems" ViewMode="Scrivenings" ScriveningsSelection="0,0">E223717E-D70B-449C-B2F9-BD8A841D3D3B</HistoryItem>
                    <HistoryItem Type="BinderItems" ViewMode="Scrivenings" ScriveningsSelection="0,0">1BF4AF98-1670-4490-A9AA-5570DE96FA8E</HistoryItem>
                    <HistoryItem Type="BinderItems" ViewMode="Single">DC012F76-010A-429A-BD5A-35EA344C9913</HistoryItem>
                    <HistoryItem Type="BinderItems" ViewMode="Scrivenings" ScriveningsSelection="0,0">F0300D21-4402-4D01-80B5-4277F737456C</HistoryItem>
                    <HistoryItem Type="BinderItems" ViewMode="Scrivenings" ScriveningsSelection="0,0">3CDB8BE9-34FC-442B-8E2C-0544816AC3B9</HistoryItem>
                    <HistoryItem Type="BinderItems" ViewMode="Scrivenings" ScriveningsSelection="0,0">F0300D21-4402-4D01-80B5-4277F737456C</HistoryItem>
                    <HistoryItem Type="BinderItems" ViewMode="Scrivenings" ScriveningsSelection="453832,0">7A583553-3A84-40D6-B9B9-0430B8CD3E39</HistoryItem>
                    <HistoryItem Type="BinderItems" ViewMode="Scrivenings" ScriveningsSelection="474,0">F2B2723C-CDC8-4C35-90B7-BCD557B66E9A</HistoryItem>
                    <HistoryItem Type="BinderItems" ViewMode="Scrivenings" ScriveningsSelection="0,0">96072CFD-D310-4AE7-B2C8-38152766E737</HistoryItem>
                    <HistoryItem Type="BinderItems" ViewMode="Scrivenings" ScriveningsSelection="0,0">226BFB73-24D3-485A-BEAE-0D717A4BA743</HistoryItem>
                    <HistoryItem Type="BinderItems" ViewMode="Single">A151F21E-9DB0-4A2E-8CC0-F258638E7524</HistoryItem>
                    <HistoryItem Type="BinderItems" ViewMode="Scrivenings" ScriveningsSelection="0,0">5823802B-C704-42B3-AD53-70CB7283790B</HistoryItem>
                    <HistoryItem Type="BinderItems" ViewMode="Single">F32091D5-63D9-4B78-B9A0-4F966A7F8004</HistoryItem>
                    <HistoryItem Type="BinderItems" ViewMode="Single">3CAFE294-7794-4E86-A7F5-D32E73C1EAFE</HistoryItem>
                </NavigationHistory>
            </View>
            <Text>
                <ShowRuler>Yes</ShowRuler>
                <PageLayout Facing="No">No</PageLayout>
                <TypewriterScrolling>No</TypewriterScrolling>
                <LineNumbers Interval="1">No</LineNumbers>
                <Selection>82,2728</Selection>
            </Text>
            <Outliner>
                <Columns>
                    <ColID>title</ColID>
                    <ColID>label</ColID>
                    <ColID>status</ColID>
                    <ColID>sectionType</ColID>
                    <ColID>totalTargetCount</ColID>
                    <ColID>totalProgress</ColID>
                </Columns>
                <TitlesOnly>No</TitlesOnly>
                <HideIcons>No</HideIcons>
                <ShowNumbers>No</ShowNumbers>
                <KeywordsAsChips>Yes</KeywordsAsChips>
                <FixedRowHeights>No</FixedRowHeights>
            </Outliner>
            <Corkboard>
                <CardsAcross>-1</CardsAcross>
                <KeywordChips>5</KeywordChips>
                <SizeCardsToFit>Yes</SizeCardsToFit>
                <CardHeightRatio>0.6666</CardHeightRatio>
                <SectionsArrangement>Wrap</SectionsArrangement>
                <LabelThreadsUseColumns>No</LabelThreadsUseColumns>
            </Corkboard>
            <Copyholder PreferredOrientation="Vertical" VerticalPos="Right" HorizontalPos="Bottom">
                <Text>
                    <ShowRuler>No</ShowRuler>
                    <PageLayout Facing="No">No</PageLayout>
                    <TypewriterScrolling>No</TypewriterScrolling>
                    <LineNumbers Interval="1">No</LineNumbers>
                </Text>
            </Copyholder>
        </Editor2>
    </Editors>
</UIStates>